helm_values_manager/__init__.py
helm_values_manager/cli.py
helm_values_manager/errors.py
helm_values_manager/generator.py
helm_values_manager/models.py
helm_values_manager/utils.py
helm_values_manager/validator.py
helm_values_manager/commands/__init__.py
helm_values_manager/commands/generate.py
helm_values_manager/commands/init.py
helm_values_manager/commands/schema.py
helm_values_manager/commands/validate.py
helm_values_manager/commands/values.py
helm_values_manager-1.0.0.dist-info/METADATA
helm_values_manager-1.0.0.dist-info/WHEEL
helm_values_manager-1.0.0.dist-info/entry_points.txt
helm_values_manager-1.0.0.dist-info/licenses/LICENSE
helm_values_manager-1.0.0.dist-info/RECORD
