Metadata-Version: 2.4
Name: helm-values-manager
Version: 1.0.0
Summary: A schema-driven tool for managing Helm values with environment-specific configurations and secret management
License-File: LICENSE
Requires-Python: >=3.9
Requires-Dist: pydantic>=2.10.6
Requires-Dist: pyyaml>=6.0.2
Requires-Dist: rich>=14.0.0
Requires-Dist: typer>=0.16.0
